becky_cli/__init__.py
becky_cli/run.py
becky_cli/becky/__init__.py
becky_cli/becky/backups/backup.py
becky_cli/becky/backups/backup_manager.py
becky_cli/becky/databases/database.py
becky_cli/becky/providers/local_provider.py
becky_cli/becky/providers/remote_provider.py
becky_cli/becky/providers/s3_provider.py
becky_cli/becky/scanners/local_differential_scanner.py
becky_cli/becky/utils/utils.py
becky_cli/tests/providers/generic_tests.py
becky_cli/tests/providers/test_local_provider.py
becky_cli/tests/providers/test_remote_provider.py
becky_cli/tests/providers/test_s3_provider.py
Becky-0.7.dist-info/LICENSE
Becky-0.7.dist-info/METADATA
Becky-0.7.dist-info/WHEEL
Becky-0.7.dist-info/entry_points.txt
Becky-0.7.dist-info/top_level.txt
Becky-0.7.dist-info/RECORD
