Metadata-Version: 2.1
Name: Becky
Version: 0.7
Summary: Becky backupper
Home-page: UNKNOWN
Author: Aleksi Vesanto
Author-email: avjves@gmail.com
License: MIT
Platform: UNKNOWN
License-File: LICENSE
